{
    "Ajmeri Gate": "3588460",
    "Alipur": "192641",
    "Anand Vihar": "3588482",
    "Anarkali": "3588456",
    "Andrews Ganj": "3588307",
    "Asola": "3351848",
    "Aya Nagar": "3351849",
    "Azad Nagar": "3588381",
    "Azadpur": "895001",
    "Badarpur": "894979",
    "Badli": "3351852",
    "Bakkar Wala": "3351855",
    "Bankner": "3351858",
    "Baprola": "3351859",
    "Batla House": "3588388",
    "Bawana": "187746",
    "Begumpur": "3351865",
    "Bhajanpura": "3588403",
    "Bhalswa": "3351869",
    "Bhati": "3351872",
    "Bhor Garh": "3351873",
    "Bijwasan": "3588387",
    "Bindapur": "3351877",
    "Budh Vihar": "3588404",
    "Burari": "3588448",
    "Chanakyapuri": "3588318",
    "Chandni Chowk": "3588439",
    "Chhatarpur": "893829",
    "Chilla Saroda Banger": "3351886",
    "Chirag Delhi": "3351888",
    "Chittaranjan Park": "3588311",
    "Connaught Place": "893664",
    "Dabri": "3351891",
    "Dakshinpuri": "3588377",
    "Daryaganj": "893524",
    "Defence Colony": "3588327",
    "Delhi": "202396",
    "Delhi Cantonment": "893482",
    "Dera Mandi": "893446",
    "Dichaon Kalan": "1798450",
    "Dilshad Garden": "3588478",
    "Dwarka": "3588465",
    "East of Kailash": "3588310",
    "G.T.B. Nagar": "3588407",
    "Geeta Colony": "3588383",
    "Ghonda": "3588406",
    "Greater Kailash": "3588309",
    "Hari Nagar": "3588394",
    "Harsh Vihar": "3588380",
    "Hastsal": "3351930",
    "IP Extention": "3588408",
    "Jahangir Puri": "3588464",
    "Jaitpur": "3351943",
    "Janak Puri": "3588393",
    "Jiwanpur": "3351949",
    "Jyoti Nagar": "3588461",
    "Kakrola": "3351959",
    "Kamal Pur": "3588449",
    "Kamla Nagar": "3588433",
    "Kamruddin Nagar": "3351961",
    "Karala": "3351965",
    "Karawal Nagar": "3351967",
    "Karol Bagh": "891786",
    "Khajuri Khas": "3351971",
    "Kirari Suleman Nagar": "3351988",
    "Lajpat Nagar": "3588347",
    "Mangolpuri": "3352011",
    "Maujpur": "3352016",
    "Mayur Vihar": "3588412",
    "Milap Nagar": "3588471",
    "Mukherjee Nagar": "3588405",
    "Mukund Pur": "3588414",
    "Mundka": "3352025",
    "Najafgarh": "197702",
    "Narela": "889947",
    "New Delhi": "187745",
    "Nilothi": "3352038",
    "Pandav Nagar": "3588424",
    "Paschim Vihar": "3588420",
    "Pitampura": "3352051",
    "Pooth Kalan": "3352053",
    "Prem Nagar": "3588477",
    "Rajendra Nagar": "3588323",
    "RK Puram": "3588374",
    "Rohini": "3588462",
    "Sadar Bazar": "3588435",
    "Sangam Vihar": "3588352",
    "Sawan Park": "3588428",
    "Seelampur": "3352095",
    "Shahdara": "888374",
    "Shalimar Bagh": "3588452",
    "Shiv Vihar": "3588441",
    "Sonia Vihar": "3588410",
    "Sultanpuri": "3352112",
    "Sunder Nagri": "3588416",
    "Tilak Nagar": "3588395",
    "Usmanpur": "3588463",
    "Vasant Kunj": "3588312",
    "Vikas Nagar": "3588398",
    "Yamuna Vihar": "3588447"
  }